sphinx_swagger_doc-0.2.2.dist-info/METADATA
sphinx_swagger_doc-0.2.2.dist-info/RECORD
sphinx_swagger_doc-0.2.2.dist-info/WHEEL
sphinx_swagger_doc-0.2.2.dist-info/top_level.txt
sphinxcontrib/__init__.py
sphinxcontrib/swaggerdoc/__init__.py
sphinxcontrib/swaggerdoc/swagger_doc.py
sphinxcontrib/swaggerdoc/swaggerv2_doc.py
