Metadata-Version: 2.1
Name: sphinx-swagger-doc
Version: 0.2.2
Summary: Sphinx extension for documenting Swagger 2.0 APIs
Home-page: https://github.com/jamrizzi/sphinx-swagger-doc
Author: Jam Risser
Author-email: jamrizzi@gmail.com
License: MIT
Platform: UNKNOWN
Classifier: Development Status :: 4 - Beta
Classifier: Environment :: Console
Classifier: Environment :: Web Environment
Classifier: Intended Audience :: Developers
Classifier: Operating System :: OS Independent
Classifier: License :: OSI Approved :: MIT License
Classifier: Programming Language :: Python
Classifier: Topic :: Documentation
Classifier: Topic :: Utilities
Requires-Dist: sphinx
Requires-Dist: requests
Requires-Dist: requests-file
Requires-Dist: future
